apis_scraper/__init__.py
apis_scraper-1.0.1.dist-info/LICENSE
apis_scraper-1.0.1.dist-info/METADATA
apis_scraper-1.0.1.dist-info/WHEEL
apis_scraper-1.0.1.dist-info/top_level.txt
apis_scraper-1.0.1.dist-info/RECORD
