Metadata-Version: 2.1
Name: apis-scraper
Version: 1.0.1
Summary: Python web scraper for getting Polish political parties support percentage
Home-page: https://github.com/TheLastGimbus/APiS-Scraper
Author: TheLastGimbus
Author-email: mateusz.soszynski@tuta.io
License: Apache
Platform: UNKNOWN
Classifier: Programming Language :: Python :: 3
Classifier: License :: OSI Approved :: Apache Software License
Classifier: Development Status :: 5 - Production/Stable
Classifier: Natural Language :: Polish
Classifier: Intended Audience :: Developers
Classifier: Intended Audience :: Education
Classifier: Intended Audience :: Information Technology
Classifier: Topic :: Religion
Classifier: Topic :: Office/Business :: News/Diary
Requires-Dist: beautifulsoup4
Requires-Dist: requests
